pyunity/__init__.py
pyunity/__main__.py
pyunity/audio.cpython-39-darwin.so
pyunity/config.cpython-39-darwin.so
pyunity/core.cpython-39-darwin.so
pyunity/errors.cpython-39-darwin.so
pyunity/files.cpython-39-darwin.so
pyunity/gui.cpython-39-darwin.so
pyunity/input.cpython-39-darwin.so
pyunity/loader.cpython-39-darwin.so
pyunity/logger.cpython-39-darwin.so
pyunity/meshes.cpython-39-darwin.so
pyunity/notes.txt
pyunity/render.cpython-39-darwin.so
pyunity/settings.cpython-39-darwin.so
pyunity/examples/__init__.py
pyunity/examples/example1/__init__.py
pyunity/examples/example10/__init__.py
pyunity/examples/example2/__init__.py
pyunity/examples/example3/__init__.py
pyunity/examples/example4/__init__.py
pyunity/examples/example5/__init__.py
pyunity/examples/example6/__init__.py
pyunity/examples/example7/__init__.py
pyunity/examples/example7/explode.ogg
pyunity/examples/example8/__init__.py
pyunity/examples/example8/logo.png
pyunity/examples/example9/__init__.py
pyunity/physics/__init__.py
pyunity/physics/config.cpython-39-darwin.so
pyunity/physics/core.cpython-39-darwin.so
pyunity/primitives/capsule.mesh
pyunity/primitives/cube.mesh
pyunity/primitives/cylinder.mesh
pyunity/primitives/double_quad.mesh
pyunity/primitives/quad.mesh
pyunity/primitives/sphere.mesh
pyunity/scenes/__init__.py
pyunity/scenes/scene.cpython-39-darwin.so
pyunity/scenes/sceneManager.cpython-39-darwin.so
pyunity/shaders/gui/button.png
pyunity/shaders/gui/fragment.glsl
pyunity/shaders/gui/vertex.glsl
pyunity/shaders/gui/textures/button.png
pyunity/shaders/gui/textures/checkboxOff.png
pyunity/shaders/gui/textures/checkboxOn.png
pyunity/shaders/skybox/fragment.glsl
pyunity/shaders/skybox/vertex.glsl
pyunity/shaders/skybox/textures/back.jpg
pyunity/shaders/skybox/textures/bottom.jpg
pyunity/shaders/skybox/textures/front.jpg
pyunity/shaders/skybox/textures/left.jpg
pyunity/shaders/skybox/textures/right.jpg
pyunity/shaders/skybox/textures/top.jpg
pyunity/shaders/standard/fragment.glsl
pyunity-0.8.4.dist-info/LICENSE
pyunity-0.8.4.dist-info/METADATA
pyunity-0.8.4.dist-info/WHEEL
pyunity-0.8.4.dist-info/top_level.txt
pyunity-0.8.4.dist-info/RECORD
